ski_weather_utah/__init__.py
ski_weather_utah/configure_cron.py
ski_weather_utah/setup_script.py
ski_weather_utah/ski_weather_utah.py
ski_weather_utah-1.4.dist-info/METADATA
ski_weather_utah-1.4.dist-info/WHEEL
ski_weather_utah-1.4.dist-info/entry_points.txt
ski_weather_utah-1.4.dist-info/top_level.txt
ski_weather_utah-1.4.dist-info/RECORD
