Metadata-Version: 2.1
Name: ski-weather-utah
Version: 1.4
Summary: A server-side app that sends daily updates for weather at select Utah ski resorts.
Author: Alex Calder
Requires-Dist: selenium
Requires-Dist: webdriver-manager
Requires-Dist: configparser
Requires-Dist: chromedriver-autoinstaller
